yzwspider/__init__.py
yzwspider/__main__.py
yzwspider/commands/__init__.py
yzwspider/commands/cmd.py
yzwspider/yzw/__init__.py
yzwspider/yzw/collector.py
yzwspider/yzw/items.py
yzwspider/yzw/pipelines.py
yzwspider/yzw/settings.py
yzwspider/yzw/start.py
yzwspider/yzw/spiders/__init__.py
yzwspider/yzw/spiders/schools.py
yzwspider/yzw/spiders/subjects.py
yzwspider-0.1.6.3.dist-info/LICENSE.txt
yzwspider-0.1.6.3.dist-info/METADATA
yzwspider-0.1.6.3.dist-info/WHEEL
yzwspider-0.1.6.3.dist-info/top_level.txt
yzwspider-0.1.6.3.dist-info/RECORD
