Metadata-Version: 2.1
Name: yzwspider
Version: 0.1.6.3
Summary: A web spider for Chinese graduate student examination catalogue.
Author-email: Hthing <hxcnly@gmail.com>
Project-URL: Homepage, https://github.com/Hthing/yzw
Classifier: Programming Language :: Python :: 3
Classifier: License :: OSI Approved :: MIT License
Classifier: Operating System :: OS Independent
Requires-Python: >=3.7
License-File: LICENSE.txt
Requires-Dist: xlwt
Requires-Dist: pymysql
Requires-Dist: scrapy
Requires-Dist: twisted
